admet_ai/__init__.py
admet_ai/admet_info.py
admet_ai/admet_model.py
admet_ai/admet_predict.py
admet_ai/constants.py
admet_ai/drugbank.py
admet_ai/physchem.py
admet_ai/plot.py
admet_ai/py.typed
admet_ai/utils.py
admet_ai/resources/data/admet.csv
admet_ai/resources/data/drugbank_approved.csv
admet_ai/resources/models/admet_classification/model_0.pt
admet_ai/resources/models/admet_classification/model_1.pt
admet_ai/resources/models/admet_classification/model_2.pt
admet_ai/resources/models/admet_classification/model_3.pt
admet_ai/resources/models/admet_classification/model_4.pt
admet_ai/resources/models/admet_regression/model_0.pt
admet_ai/resources/models/admet_regression/model_1.pt
admet_ai/resources/models/admet_regression/model_2.pt
admet_ai/resources/models/admet_regression/model_3.pt
admet_ai/resources/models/admet_regression/model_4.pt
admet_ai/web/__init__.py
admet_ai/web/run.py
admet_ai/web/wsgi.py
admet_ai/web/app/__init__.py
admet_ai/web/app/config.py
admet_ai/web/app/models.py
admet_ai/web/app/storage.py
admet_ai/web/app/utils.py
admet_ai/web/app/views.py
admet_ai/web/app/static/images/ADMET.jpg
admet_ai/web/app/static/images/absorption.jpg
admet_ai/web/app/static/images/distribution.jpg
admet_ai/web/app/static/images/excretion.jpg
admet_ai/web/app/static/images/metabolism.jpg
admet_ai/web/app/static/images/physicochemical.jpg
admet_ai/web/app/static/images/toxicity.jpg
admet_ai/web/app/static/jsme/JME_to_JSME.html
admet_ai/web/app/static/jsme/JME_to_JSME_simple.html
admet_ai/web/app/static/jsme/JSME_Rgroups.html
admet_ai/web/app/static/jsme/JSME_SVG.html
admet_ai/web/app/static/jsme/JSME_access_internal_data.html
admet_ai/web/app/static/jsme/JSME_additional_data.html
admet_ai/web/app/static/jsme/JSME_alternative_look.html
admet_ai/web/app/static/jsme/JSME_atom_highlight_demo.html
admet_ai/web/app/static/jsme/JSME_autoresize.html
admet_ai/web/app/static/jsme/JSME_callback_and_mark.html
admet_ai/web/app/static/jsme/JSME_chemical_resolver_demo.html
admet_ai-1.4.0.dist-info/licenses/LICENSE.txt
admet_ai-1.4.0.dist-info/METADATA
admet_ai-1.4.0.dist-info/WHEEL
admet_ai-1.4.0.dist-info/entry_points.txt
admet_ai-1.4.0.dist-info/top_level.txt
admet_ai-1.4.0.dist-info/RECORD
