Metadata-Version: 2.4
Name: admet_ai
Version: 1.4.0
Summary: ADMET-AI
Author-email: Kyle Swanson <swansonk.14@gmail.com>
Maintainer-email: Kyle Swanson <swansonk.14@gmail.com>
License-Expression: MIT
Project-URL: Homepage, https://github.com/swansonk14/admet_ai
Project-URL: Issues, https://github.com/swansonk14/admet_ai/issues
Keywords: machine learning,drug design,ADMET,molecular property prediction
Classifier: Programming Language :: Python :: 3
Classifier: Programming Language :: Python :: 3.10
Classifier: Programming Language :: Python :: 3.11
Classifier: Programming Language :: Python :: 3.12
Classifier: Operating System :: OS Independent
Classifier: Typing :: Typed
Requires-Python: <3.13,>=3.10
License-File: LICENSE.txt
Requires-Dist: chemfunc>=1.0.4
Requires-Dist: chemprop==1.6.1
Requires-Dist: numpy
Requires-Dist: pandas<2.2.0,>=2.0.0
Requires-Dist: rdkit>=2023.3.3
Requires-Dist: seaborn
Requires-Dist: torch==2.5.0
Requires-Dist: tqdm
Requires-Dist: typed-argument-parser>=1.9.0
Provides-Extra: tdc
Requires-Dist: openpyxl; extra == "tdc"
Requires-Dist: PyTDC>=0.4.1; extra == "tdc"
Provides-Extra: web
Requires-Dist: flask; extra == "web"
Requires-Dist: gunicorn; extra == "web"
Dynamic: license-file
